eeg_positions/__init__.py
eeg_positions/compute.py
eeg_positions/config.py
eeg_positions/utils.py
eeg_positions/viz.py
eeg_positions-2.1.1.dist-info/METADATA
eeg_positions-2.1.1.dist-info/WHEEL
eeg_positions-2.1.1.dist-info/licenses/LICENSE
eeg_positions-2.1.1.dist-info/RECORD
